PandasMijiChuyi/README.md
PandasMijiChuyi/__init__.py
PandasMijiChuyi/__main__.py
PandasMijiChuyi/file.epub
PandasMijiChuyi/index.html
PandasMijiChuyi/css/__init__.py
PandasMijiChuyi/css/annotations.css
PandasMijiChuyi/css/main.css
PandasMijiChuyi/css/normalize.css
PandasMijiChuyi/css/popup.css
PandasMijiChuyi/font/__init__.py
PandasMijiChuyi/font/fontello.eot
PandasMijiChuyi/font/fontello.svg
PandasMijiChuyi/font/fontello.ttf
PandasMijiChuyi/font/fontello.woff
PandasMijiChuyi/img/__init__.py
PandasMijiChuyi/img/annotator-glyph-sprite.png
PandasMijiChuyi/img/annotator-icon-sprite.png
PandasMijiChuyi/img/apple-touch-icon.png
PandasMijiChuyi/img/cancelfullscreen.png
PandasMijiChuyi/img/close.png
PandasMijiChuyi/img/fullscreen.png
PandasMijiChuyi/img/loader.gif
PandasMijiChuyi/img/menu-icon.png
PandasMijiChuyi/img/save.png
PandasMijiChuyi/img/saved.png
PandasMijiChuyi/img/settings-s.png
PandasMijiChuyi/img/settings.png
PandasMijiChuyi/img/star.png
PandasMijiChuyi/js/__init__.py
PandasMijiChuyi/js/epub.js
PandasMijiChuyi/js/epub.min.js
PandasMijiChuyi/js/epub.min.map
PandasMijiChuyi/js/hooks.min.js
PandasMijiChuyi/js/hooks.min.map
PandasMijiChuyi/js/reader.js
PandasMijiChuyi/js/reader.js.map
PandasMijiChuyi/js/reader.min.js
PandasMijiChuyi/js/reader.min.map
PandasMijiChuyi/js/hooks/__init__.py
PandasMijiChuyi/js/hooks/extensions/__init__.py
PandasMijiChuyi/js/hooks/extensions/highlight.js
PandasMijiChuyi/js/libs/__init__.py
PandasMijiChuyi/js/libs/jquery.min.js
PandasMijiChuyi/js/libs/localforage.min.js
PandasMijiChuyi/js/libs/screenfull.js
PandasMijiChuyi/js/libs/screenfull.min.js
PandasMijiChuyi/js/libs/zip.min.js
PandasMijiChuyi/js/plugins/__init__.py
PandasMijiChuyi/js/plugins/hypothesis.js
PandasMijiChuyi/js/plugins/search.js
pandas_miji_chuyi-2024.3.5.0.dist-info/METADATA
pandas_miji_chuyi-2024.3.5.0.dist-info/WHEEL
pandas_miji_chuyi-2024.3.5.0.dist-info/entry_points.txt
pandas_miji_chuyi-2024.3.5.0.dist-info/top_level.txt
pandas_miji_chuyi-2024.3.5.0.dist-info/RECORD
